hyperspyui/__init__.py
hyperspyui/__main__.py
hyperspyui/_elements.py
hyperspyui/actionable.py
hyperspyui/advancedaction.py
hyperspyui/bindinglist.py
hyperspyui/desktop_integration.py
hyperspyui/desktop_integration_linux.py
hyperspyui/desktop_integration_windows.py
hyperspyui/exceptions.py
hyperspyui/hooksignal.py
hyperspyui/hooktraitsui.py
hyperspyui/log.py
hyperspyui/mainwindow.py
hyperspyui/mainwindowbase.py
hyperspyui/mainwindowhyperspy.py
hyperspyui/mainwindowutillayer.py
hyperspyui/mdi_mpl_backend.py
hyperspyui/modelwrapper.py
hyperspyui/overrides.py
hyperspyui/plugincreator.py
hyperspyui/pluginmanager.py
hyperspyui/recorder.py
hyperspyui/settings.py
hyperspyui/signalwrapper.py
hyperspyui/singleapplication.py
hyperspyui/smartcolorsvgiconengine.py
hyperspyui/threaded.py
hyperspyui/tools.py
hyperspyui/uiprogressbar.py
hyperspyui/util.py
hyperspyui/_tools/__init__.py
hyperspyui/_tools/figuretool.py
hyperspyui/_tools/gaussiantool.py
hyperspyui/_tools/hometool.py
hyperspyui/_tools/linetool.py
hyperspyui/_tools/multiselectiontool.py
hyperspyui/_tools/pointertool.py
hyperspyui/_tools/selectiontool.py
hyperspyui/_tools/signalfiguretool.py
hyperspyui/_tools/tool.py
hyperspyui/_tools/zoompan.py
hyperspyui/images/3d.svg
hyperspyui/images/Hypercube.svg
hyperspyui/images/add.svg
hyperspyui/images/align2d.svg
hyperspyui/images/align_horizontal.svg
hyperspyui/images/align_manual.svg
hyperspyui/images/align_vertical.svg
hyperspyui/images/align_zero_loss.svg
hyperspyui/images/analysis.svg
hyperspyui/images/attributions.txt
hyperspyui/images/bss.svg
hyperspyui/images/candlestick.svg
hyperspyui/images/chart.svg
hyperspyui/images/chart_column.svg
hyperspyui/images/chart_horz.svg
hyperspyui/images/chart_stacked_column.svg
hyperspyui/images/close.svg
hyperspyui/images/close_window.svg
hyperspyui/images/close_windows.svg
hyperspyui/images/console.svg
hyperspyui/images/crop.svg
hyperspyui/images/divide.svg
hyperspyui/images/download.svg
hyperspyui/images/fft.svg
hyperspyUI-2.0.2.dist-info/COPYING.txt
hyperspyUI-2.0.2.dist-info/METADATA
hyperspyUI-2.0.2.dist-info/WHEEL
hyperspyUI-2.0.2.dist-info/entry_points.txt
hyperspyUI-2.0.2.dist-info/top_level.txt
hyperspyUI-2.0.2.dist-info/RECORD
