Metadata-Version: 2.2
Name: hyperspyUI
Version: 2.0.2
Summary: Hyperspy Graphical User Interface
License:                     GNU GENERAL PUBLIC LICENSE
Project-URL: Homepage, https://hyperspy.org/hyperspyui
Project-URL: Bug Reports, https://github.com/hyperspy/hyperspyui/issues
Project-URL: Source, https://github.com/hyperspy/hyperspyui
Keywords: data analysis,microscopy,electron microscopy,electron energy loss spectroscopy,X-ray energy-dispersive spectroscopy
Classifier: Development Status :: 4 - Beta
Classifier: Intended Audience :: Developers
Classifier: Intended Audience :: Science/Research
Classifier: Topic :: Software Development :: Libraries
Classifier: Topic :: Scientific/Engineering
Classifier: Topic :: Scientific/Engineering :: Physics
Classifier: License :: OSI Approved :: GNU General Public License v3 (GPLv3)
Classifier: Programming Language :: Python :: 3.9
Classifier: Programming Language :: Python :: 3.10
Classifier: Programming Language :: Python :: 3.11
Classifier: Programming Language :: Python :: 3.12
Classifier: Operating System :: Microsoft :: Windows
Classifier: Operating System :: POSIX
Classifier: Operating System :: Unix
Classifier: Operating System :: MacOS
Requires-Python: >=3.8
License-File: COPYING.txt
Requires-Dist: exspy>=0.3.1
Requires-Dist: hyperspy>=2.0rc0
Requires-Dist: hyperspy-gui-traitsui>=2.0
Requires-Dist: matplotlib>=3.6.1
Requires-Dist: packaging
Requires-Dist: pyqode.python>=4.0.2
Requires-Dist: pyqode.core>=4.0.10
Requires-Dist: pyface>=6.0.0
Requires-Dist: pyflakes
Requires-Dist: pywin32>=1.0; platform_system == "Windows"
Requires-Dist: autopep8
Requires-Dist: traits
Requires-Dist: traitsui>=5.2.0
Requires-Dist: qtconsole>=5.2.0
Requires-Dist: ipykernel<7,>=5.2.0
Requires-Dist: qtpy
Provides-Extra: all
Requires-Dist: exspy; extra == "all"
Requires-Dist: hyperspyui[pyqt]; extra == "all"
Provides-Extra: doc
Requires-Dist: pydata_sphinx_theme; extra == "doc"
Requires-Dist: sphinx>5.2; extra == "doc"
Requires-Dist: sphinx_design; extra == "doc"
Requires-Dist: sphinx-copybutton; extra == "doc"
Requires-Dist: sphinx-favicon; extra == "doc"
Requires-Dist: sphinxcontrib-towncrier; extra == "doc"
Requires-Dist: towncrier<24; extra == "doc"
Provides-Extra: pyqt
Requires-Dist: PyQt5; extra == "pyqt"
Requires-Dist: PyQtWebEngine; extra == "pyqt"
Provides-Extra: tests
Requires-Dist: pytest-qt; extra == "tests"
Requires-Dist: pytest-cov; extra == "tests"
Requires-Dist: pytest-timeout; extra == "tests"
Requires-Dist: setuptools-scm; extra == "tests"
